jp_1/__init__.py
jp_1/module_1_jp_1.py
jp_1/module_2_jp_1.py
jp_2/__init__.py
jp_2/module_1_jp_2 copy.py
jp_2/module_2_jp_2.py
jp1924_setup_testing-0.5.dist-info/METADATA
jp1924_setup_testing-0.5.dist-info/WHEEL
jp1924_setup_testing-0.5.dist-info/top_level.txt
jp1924_setup_testing-0.5.dist-info/RECORD
