Metadata-Version: 2.1
Name: jp1924-setup-testing
Version: 0.5
Summary: ['testing pypi upload']
Home-page: https://github.com/jp1924/pypi_upload
Author: jp
Author-email: jsb1012129@gmail.com
License: UNKNOWN
Platform: UNKNOWN
Requires-Python: >=3.6.0
Requires-Dist: wheel
Requires-Dist: setuptools
